dicomsdl/_dicomsdl.cpython-312-x86_64-linux-musl.so
dicomsdl/util.py
dicomsdl/dump.py
dicomsdl/show.py
dicomsdl/_util.cpython-312-x86_64-linux-musl.so
dicomsdl/__init__.py
dicomsdl.libs/libgcc_s-a04fdf82.so.1
dicomsdl.libs/libstdc++-a9383cce.so.6.0.28
dicomsdl-0.109.4.dist-info/WHEEL
dicomsdl-0.109.4.dist-info/METADATA
dicomsdl-0.109.4.dist-info/RECORD
dicomsdl-0.109.4.dist-info/entry_points.txt
dicomsdl-0.109.4.dist-info/top_level.txt
dicomsdl-0.109.4.dist-info/LICENSE
